{
 "ticker": "0098F0",
 "name": "KODEX 원자력SMR",
 "manager": "KODEX",
 "source": "삼성 KODEX",
 "asof": "2026-07-14",
 "total_weight": 100.01,
 "count": 15,
 "holdings": [
  {
   "code": "000720",
   "name": "현대건설",
   "weight": 19.76,
   "shares": 1378.0,
   "amount": 139867000.0,
   "over_cap": false
  },
  {
   "code": "034020",
   "name": "두산에너빌리티",
   "weight": 19.75,
   "shares": 1909.0,
   "amount": 139738800.0,
   "over_cap": false
  },
  {
   "code": "047040",
   "name": "대우건설",
   "weight": 9.35,
   "shares": 4135.0,
   "amount": 66201350.0,
   "over_cap": false
  },
  {
   "code": "375500",
   "name": "DL이앤씨",
   "weight": 8.18,
   "shares": 960.0,
   "amount": 57888000.0,
   "over_cap": false
  },
  {
   "code": "015760",
   "name": "한국전력",
   "weight": 7.98,
   "shares": 1649.0,
   "amount": 56478250.0,
   "over_cap": false
  },
  {
   "code": "028260",
   "name": "삼성물산",
   "weight": 7.35,
   "shares": 144.0,
   "amount": 51984000.0,
   "over_cap": false
  },
  {
   "code": "052690",
   "name": "한전기술",
   "weight": 7.01,
   "shares": 508.0,
   "amount": 49580800.0,
   "over_cap": false
  },
  {
   "code": "032820",
   "name": "우리기술",
   "weight": 6.36,
   "shares": 4210.0,
   "amount": 45004900.0,
   "over_cap": false
  },
  {
   "code": "051600",
   "name": "한전KPS",
   "weight": 4.66,
   "shares": 748.0,
   "amount": 32949400.0,
   "over_cap": false
  },
  {
   "code": "083650",
   "name": "비에이치아이",
   "weight": 4.55,
   "shares": 694.0,
   "amount": 32166900.0,
   "over_cap": false
  },
  {
   "code": "014620",
   "name": "성광벤드",
   "weight": 1.92,
   "shares": 513.0,
   "amount": 13594500.0,
   "over_cap": false
  },
  {
   "code": "130660",
   "name": "한전산업",
   "weight": 0.97,
   "shares": 643.0,
   "amount": 6880100.0,
   "over_cap": false
  },
  {
   "code": "105840",
   "name": "우진",
   "weight": 0.92,
   "shares": 460.0,
   "amount": 6486000.0,
   "over_cap": false
  },
  {
   "code": "044490",
   "name": "태웅",
   "weight": 0.85,
   "shares": 226.0,
   "amount": 6034200.0,
   "over_cap": false
  },
  {
   "code": "094820",
   "name": "일진파워",
   "weight": 0.4,
   "shares": 257.0,
   "amount": 2816720.0,
   "over_cap": false
  }
 ],
 "breach_summary": null,
 "cap": {
  "single_cap": null,
  "index_exception": true,
  "label": "비중상한 미확인 · 확인 요",
  "source": "지수 방법론/투자설명서 원문 미확인",
  "verified": false,
  "note": "자체 비중상한이 있을 수 있으나 방법론 원문을 확인하지 못했다. 잘못된 매도경고를 피하기 위해 cap 초과 판정을 보류한다. 정확한 상한은 지수 방법론/투자설명서 확인 필요."
 }
}