{
 "ticker": "0141S0",
 "name": "SOL 조선기자재",
 "manager": "SOL",
 "source": "신한 SOL",
 "asof": "2026-07-14",
 "total_weight": 100.0,
 "count": 11,
 "holdings": [
  {
   "code": "443060",
   "name": "HD현대마린솔루션",
   "weight": 25.41,
   "shares": 564.0,
   "amount": 109190400.0,
   "over_cap": true
  },
  {
   "code": "082740",
   "name": "한화엔진",
   "weight": 17.87,
   "shares": 1662.0,
   "amount": 76784400.0,
   "over_cap": false
  },
  {
   "code": "017960",
   "name": "한국카본",
   "weight": 17.33,
   "shares": 3027.0,
   "amount": 74464200.0,
   "over_cap": false
  },
  {
   "code": "071970",
   "name": "HD현대마린엔진",
   "weight": 15.03,
   "shares": 1084.0,
   "amount": 64606400.0,
   "over_cap": false
  },
  {
   "code": "439260",
   "name": "대한조선",
   "weight": 5.52,
   "shares": 511.0,
   "amount": 23735950.0,
   "over_cap": false
  },
  {
   "code": "014620",
   "name": "성광벤드",
   "weight": 5.15,
   "shares": 835.0,
   "amount": 22127500.0,
   "over_cap": false
  },
  {
   "code": "077970",
   "name": "STX엔진",
   "weight": 4.45,
   "shares": 750.0,
   "amount": 19125000.0,
   "over_cap": false
  },
  {
   "code": "023160",
   "name": "태광",
   "weight": 3.48,
   "shares": 661.0,
   "amount": 14938600.0,
   "over_cap": false
  },
  {
   "code": "033500",
   "name": "동성화인텍",
   "weight": 3.28,
   "shares": 855.0,
   "amount": 14098950.0,
   "over_cap": false
  },
  {
   "code": "075580",
   "name": "세진중공업",
   "weight": 2.73,
   "shares": 1034.0,
   "amount": 11735900.0,
   "over_cap": false
  },
  {
   "code": "KRD010010001",
   "name": "현금성자산",
   "weight": -0.25,
   "shares": -1060517.0,
   "amount": -1060517.0,
   "over_cap": false
  }
 ],
 "breach_summary": {
  "cap_pct": 20.0,
  "verified": true,
  "count": 1,
  "total_sell": 3327150000,
  "items": [
   {
    "code": "443060",
    "name": "HD현대마린솔루션",
    "weight": 25.41,
    "cap_pct": 20.0,
    "excess_pp": 5.41,
    "sell_amount": 3327150000
   }
  ]
 },
 "cap": {
  "single_cap": 0.2,
  "index_exception": false,
  "label": "단일종목 20% 상한",
  "source": "FnGuide Shipbuilding Equipment Index Methodology v1.0: 20% 실링; 2·5·8·11월 D+2",
  "verified": true,
  "note": "1·4·7·10월말 선정, 2·5·8·11월 만기일 D+2 정기변경"
 }
}