{
 "ticker": "266160",
 "name": "RISE 고배당",
 "manager": "RISE",
 "source": "KB RISE",
 "asof": "2026-07-17",
 "total_weight": 99.95,
 "count": 80,
 "holdings": [
  {
   "code": "000660",
   "name": "SK하이닉스",
   "weight": 28.07,
   "shares": 240.0,
   "amount": 499680000.0,
   "over_cap": true
  },
  {
   "code": "005930",
   "name": "삼성전자",
   "weight": 25.37,
   "shares": 1616.0,
   "amount": 451672000.0,
   "over_cap": true
  },
  {
   "code": "000270",
   "name": "기아",
   "weight": 6.78,
   "shares": 833.0,
   "amount": 120785000.0,
   "over_cap": false
  },
  {
   "code": "105560",
   "name": "KB금융",
   "weight": 4.38,
   "shares": 429.0,
   "amount": 77906400.0,
   "over_cap": false
  },
  {
   "code": "055550",
   "name": "신한지주",
   "weight": 3.33,
   "shares": 553.0,
   "amount": 59336900.0,
   "over_cap": false
  },
  {
   "code": "086790",
   "name": "하나금융지주",
   "weight": 3.05,
   "shares": 397.0,
   "amount": 54309600.0,
   "over_cap": false
  },
  {
   "code": "005380",
   "name": "현대차",
   "weight": 2.97,
   "shares": 122.0,
   "amount": 52948000.0,
   "over_cap": false
  },
  {
   "code": "316140",
   "name": "우리금융지주",
   "weight": 2.37,
   "shares": 1348.0,
   "amount": 42192400.0,
   "over_cap": false
  },
  {
   "code": "000810",
   "name": "삼성화재",
   "weight": 2.19,
   "shares": 59.0,
   "amount": 38999000.0,
   "over_cap": false
  },
  {
   "code": "024110",
   "name": "기업은행",
   "weight": 2.01,
   "shares": 1688.0,
   "amount": 35870000.0,
   "over_cap": false
  },
  {
   "code": "033780",
   "name": "KT&G",
   "weight": 1.42,
   "shares": 147.0,
   "amount": 25357500.0,
   "over_cap": false
  },
  {
   "code": "030200",
   "name": "KT",
   "weight": 1.22,
   "shares": 418.0,
   "amount": 21736000.0,
   "over_cap": false
  },
  {
   "code": "005830",
   "name": "DB손해보험",
   "weight": 1.08,
   "shares": 118.0,
   "amount": 19175000.0,
   "over_cap": false
  },
  {
   "code": "005940",
   "name": "NH투자증권",
   "weight": 1.05,
   "shares": 599.0,
   "amount": 18628900.0,
   "over_cap": false
  },
  {
   "code": "071050",
   "name": "한국금융지주",
   "weight": 0.99,
   "shares": 75.0,
   "amount": 17625000.0,
   "over_cap": false
  },
  {
   "code": "003550",
   "name": "LG",
   "weight": 0.9,
   "shares": 157.0,
   "amount": 16076800.0,
   "over_cap": false
  },
  {
   "code": "016360",
   "name": "삼성증권",
   "weight": 0.76,
   "shares": 122.0,
   "amount": 13554200.0,
   "over_cap": false
  },
  {
   "code": "161390",
   "name": "한국타이어앤테크놀로지",
   "weight": 0.76,
   "shares": 190.0,
   "amount": 13585000.0,
   "over_cap": false
  },
  {
   "code": "078930",
   "name": "GS",
   "weight": 0.7,
   "shares": 152.0,
   "amount": 12433600.0,
   "over_cap": false
  },
  {
   "code": "029780",
   "name": "삼성카드",
   "weight": 0.66,
   "shares": 248.0,
   "amount": 11792400.0,
   "over_cap": false
  },
  {
   "code": "039490",
   "name": "키움증권",
   "weight": 0.59,
   "shares": 32.0,
   "amount": 10592000.0,
   "over_cap": false
  },
  {
   "code": "032640",
   "name": "LG유플러스",
   "weight": 0.58,
   "shares": 733.0,
   "amount": 10408600.0,
   "over_cap": false
  },
  {
   "code": "175330",
   "name": "JB금융지주",
   "weight": 0.57,
   "shares": 361.0,
   "amount": 10071900.0,
   "over_cap": false
  },
  {
   "code": "138930",
   "name": "BNK금융지주",
   "weight": 0.57,
   "shares": 558.0,
   "amount": 10166760.0,
   "over_cap": false
  },
  {
   "code": "047050",
   "name": "포스코인터내셔널",
   "weight": 0.53,
   "shares": 185.0,
   "amount": 9509000.0,
   "over_cap": false
  },
  {
   "code": "031210",
   "name": "서울보증보험",
   "weight": 0.44,
   "shares": 185.0,
   "amount": 7760750.0,
   "over_cap": false
  },
  {
   "code": "KRD010010001",
   "name": "원화예금",
   "weight": 0.4,
   "shares": 7076116.0,
   "amount": 7076116.0,
   "over_cap": false
  },
  {
   "code": "035250",
   "name": "강원랜드",
   "weight": 0.39,
   "shares": 488.0,
   "amount": 6978400.0,
   "over_cap": false
  },
  {
   "code": "081660",
   "name": "미스토홀딩스",
   "weight": 0.29,
   "shares": 113.0,
   "amount": 5101950.0,
   "over_cap": false
  },
  {
   "code": "030000",
   "name": "제일기획",
   "weight": 0.28,
   "shares": 268.0,
   "amount": 4966040.0,
   "over_cap": false
  },
  {
   "code": "139130",
   "name": "iM금융지주",
   "weight": 0.27,
   "shares": 261.0,
   "amount": 4731930.0,
   "over_cap": false
  },
  {
   "code": "026960",
   "name": "동서",
   "weight": 0.26,
   "shares": 187.0,
   "amount": 4637600.0,
   "over_cap": false
  },
  {
   "code": "003690",
   "name": "코리안리",
   "weight": 0.25,
   "shares": 324.0,
   "amount": 4497120.0,
   "over_cap": false
  },
  {
   "code": "000240",
   "name": "한국앤컴퍼니",
   "weight": 0.24,
   "shares": 173.0,
   "amount": 4307700.0,
   "over_cap": false
  },
  {
   "code": "012750",
   "name": "에스원",
   "weight": 0.24,
   "shares": 61.0,
   "amount": 4343200.0,
   "over_cap": false
  },
  {
   "code": "005850",
   "name": "에스엘",
   "weight": 0.23,
   "shares": 75.0,
   "amount": 4117500.0,
   "over_cap": false
  },
  {
   "code": "002380",
   "name": "KCC",
   "weight": 0.22,
   "shares": 9.0,
   "amount": 3883500.0,
   "over_cap": false
  },
  {
   "code": "383220",
   "name": "F&F",
   "weight": 0.22,
   "shares": 51.0,
   "amount": 4003500.0,
   "over_cap": false
  },
  {
   "code": "009970",
   "name": "영원무역홀딩스",
   "weight": 0.17,
   "shares": 16.0,
   "amount": 3011200.0,
   "over_cap": false
  },
  {
   "code": "028670",
   "name": "팬오션",
   "weight": 0.16,
   "shares": 561.0,
   "amount": 2928420.0,
   "over_cap": false
  },
  {
   "code": "023590",
   "name": "다우기술",
   "weight": 0.15,
   "shares": 75.0,
   "amount": 2692500.0,
   "over_cap": false
  },
  {
   "code": "018670",
   "name": "SK가스",
   "weight": 0.15,
   "shares": 12.0,
   "amount": 2718000.0,
   "over_cap": false
  },
  {
   "code": "282330",
   "name": "BGF리테일",
   "weight": 0.15,
   "shares": 21.0,
   "amount": 2595600.0,
   "over_cap": false
  },
  {
   "code": "001120",
   "name": "LX인터내셔널",
   "weight": 0.14,
   "shares": 67.0,
   "amount": 2458900.0,
   "over_cap": false
  },
  {
   "code": "001800",
   "name": "오리온홀딩스",
   "weight": 0.14,
   "shares": 99.0,
   "amount": 2544300.0,
   "over_cap": false
  },
  {
   "code": "071320",
   "name": "지역난방공사",
   "weight": 0.14,
   "shares": 39.0,
   "amount": 2523300.0,
   "over_cap": false
  },
  {
   "code": "004800",
   "name": "효성",
   "weight": 0.13,
   "shares": 16.0,
   "amount": 2372800.0,
   "over_cap": false
  },
  {
   "code": "089860",
   "name": "롯데렌탈",
   "weight": 0.11,
   "shares": 58.0,
   "amount": 1972000.0,
   "over_cap": false
  },
  {
   "code": "192400",
   "name": "쿠쿠홀딩스",
   "weight": 0.1,
   "shares": 73.0,
   "amount": 1861500.0,
   "over_cap": false
  },
  {
   "code": "214320",
   "name": "이노션",
   "weight": 0.1,
   "shares": 95.0,
   "amount": 1761300.0,
   "over_cap": false
  },
  {
   "code": "036530",
   "name": "SNT홀딩스",
   "weight": 0.1,
   "shares": 35.0,
   "amount": 1760500.0,
   "over_cap": false
  },
  {
   "code": "005440",
   "name": "현대지에프홀딩스",
   "weight": 0.1,
   "shares": 131.0,
   "amount": 1789460.0,
   "over_cap": false
  },
  {
   "code": "007340",
   "name": "DN오토모티브",
   "weight": 0.1,
   "shares": 43.0,
   "amount": 1790950.0,
   "over_cap": false
  },
  {
   "code": "003540",
   "name": "대신증권",
   "weight": 0.08,
   "shares": 57.0,
   "amount": 1496250.0,
   "over_cap": false
  },
  {
   "code": "064960",
   "name": "SNT모티브",
   "weight": 0.08,
   "shares": 52.0,
   "amount": 1372800.0,
   "over_cap": false
  },
  {
   "code": "067160",
   "name": "SOOP",
   "weight": 0.08,
   "shares": 29.0,
   "amount": 1365900.0,
   "over_cap": false
  },
  {
   "code": "069260",
   "name": "TKG휴켐스",
   "weight": 0.07,
   "shares": 81.0,
   "amount": 1258740.0,
   "over_cap": false
  },
  {
   "code": "004490",
   "name": "세방전지",
   "weight": 0.07,
   "shares": 24.0,
   "amount": 1320000.0,
   "over_cap": false
  },
  {
   "code": "003570",
   "name": "SNT다이내믹스",
   "weight": 0.07,
   "shares": 37.0,
   "amount": 1283900.0,
   "over_cap": false
  },
  {
   "code": "003470",
   "name": "유안타증권",
   "weight": 0.07,
   "shares": 282.0,
   "amount": 1278870.0,
   "over_cap": false
  },
  {
   "code": "005180",
   "name": "빙그레",
   "weight": 0.06,
   "shares": 16.0,
   "amount": 1032000.0,
   "over_cap": false
  },
  {
   "code": "025540",
   "name": "한국단자",
   "weight": 0.06,
   "shares": 16.0,
   "amount": 1022400.0,
   "over_cap": false
  },
  {
   "code": "215200",
   "name": "메가스터디교육",
   "weight": 0.06,
   "shares": 29.0,
   "amount": 1113600.0,
   "over_cap": false
  },
  {
   "code": "105630",
   "name": "한세실업",
   "weight": 0.05,
   "shares": 94.0,
   "amount": 855400.0,
   "over_cap": false
  },
  {
   "code": "069080",
   "name": "웹젠",
   "weight": 0.05,
   "shares": 77.0,
   "amount": 860090.0,
   "over_cap": false
  },
  {
   "code": "056190",
   "name": "SFA",
   "weight": 0.05,
   "shares": 39.0,
   "amount": 854100.0,
   "over_cap": false
  },
  {
   "code": "016380",
   "name": "KG스틸",
   "weight": 0.05,
   "shares": 164.0,
   "amount": 836400.0,
   "over_cap": false
  },
  {
   "code": "017940",
   "name": "E1",
   "weight": 0.05,
   "shares": 11.0,
   "amount": 938300.0,
   "over_cap": false
  },
  {
   "code": "284740",
   "name": "쿠쿠홈시스",
   "weight": 0.05,
   "shares": 46.0,
   "amount": 963700.0,
   "over_cap": false
  },
  {
   "code": "453340",
   "name": "현대그린푸드",
   "weight": 0.05,
   "shares": 50.0,
   "amount": 901500.0,
   "over_cap": false
  },
  {
   "code": "383800",
   "name": "LX홀딩스",
   "weight": 0.04,
   "shares": 102.0,
   "amount": 775200.0,
   "over_cap": false
  },
  {
   "code": "005810",
   "name": "풍산홀딩스",
   "weight": 0.04,
   "shares": 22.0,
   "amount": 739200.0,
   "over_cap": false
  },
  {
   "code": "034310",
   "name": "NICE",
   "weight": 0.04,
   "shares": 61.0,
   "amount": 703940.0,
   "over_cap": false
  },
  {
   "code": "093050",
   "name": "LF",
   "weight": 0.04,
   "shares": 32.0,
   "amount": 707200.0,
   "over_cap": false
  },
  {
   "code": "091700",
   "name": "파트론",
   "weight": 0.03,
   "shares": 90.0,
   "amount": 527400.0,
   "over_cap": false
  },
  {
   "code": "078340",
   "name": "컴투스",
   "weight": 0.03,
   "shares": 22.0,
   "amount": 564300.0,
   "over_cap": false
  },
  {
   "code": "060980",
   "name": "HL홀딩스",
   "weight": 0.03,
   "shares": 16.0,
   "amount": 596000.0,
   "over_cap": false
  },
  {
   "code": "020000",
   "name": "한섬",
   "weight": 0.03,
   "shares": 25.0,
   "amount": 542500.0,
   "over_cap": false
  },
  {
   "code": "306200",
   "name": "세아제강",
   "weight": 0.03,
   "shares": 4.0,
   "amount": 496800.0,
   "over_cap": false
  },
  {
   "code": "030610",
   "name": "교보증권",
   "weight": 0.02,
   "shares": 28.0,
   "amount": 277760.0,
   "over_cap": false
  }
 ],
 "breach_summary": {
  "cap_pct": 25.0,
  "verified": true,
  "count": 2,
  "total_sell": 7389825200,
  "items": [
   {
    "code": "000660",
    "name": "SK하이닉스",
    "weight": 28.07,
    "cap_pct": 25.0,
    "excess_pp": 3.07,
    "sell_amount": 6594989350
   },
   {
    "code": "005930",
    "name": "삼성전자",
    "weight": 25.37,
    "cap_pct": 25.0,
    "excess_pp": 0.37,
    "sell_amount": 794835850
   }
  ]
 },
 "cap": {
  "single_cap": 0.25,
  "index_exception": false,
  "top_n": null,
  "top_cap": 0.25,
  "rest_cap": 0.08,
  "label": "상위 None종목 각 25% · 나머지 8%",
  "source": "FnGuide_High_Dividend_Focus_Index_Methodology_Book_KB_(20200508)_v2.1.pdf | '유동시총 비중 10% 이상 종목 = Min{25%, 유동시총} 실링 / 나머지 종목 = 8% 실링'; '4월말 종가로 종목선정…5월 선물옵션 만기일 익주 두번째 영업일에 정기변경'",
  "verified": true,
  "note": "상위 종목 상한 기준으로 초과를 계산한다(보수적). 연1회, 4월말 종가 종목선정 → 5월 선물옵션 만기일 익주 두번째 영업일 정기변경. 대형종목(MKF중대형 유동시총 10%↑)=Min{25%,유동시총}, 나머지 8% 상한"
 }
}