{
 "ticker": "292190",
 "name": "KODEX KRX300",
 "manager": "KODEX",
 "source": "삼성 KODEX",
 "asof": "2026-07-14",
 "total_weight": 99.98,
 "count": 300,
 "holdings": [
  {
   "code": "005930",
   "name": "삼성전자",
   "weight": 31.31,
   "shares": 5877.0,
   "amount": 1495696500.0,
   "over_cap": false
  },
  {
   "code": "000660",
   "name": "SK하이닉스",
   "weight": 26.96,
   "shares": 698.0,
   "amount": 1287810000.0,
   "over_cap": false
  },
  {
   "code": "402340",
   "name": "SK스퀘어",
   "weight": 2.82,
   "shares": 116.0,
   "amount": 134676000.0,
   "over_cap": false
  },
  {
   "code": "009150",
   "name": "삼성전기",
   "weight": 1.89,
   "shares": 70.0,
   "amount": 90230000.0,
   "over_cap": false
  },
  {
   "code": "005380",
   "name": "현대차",
   "weight": 1.6,
   "shares": 172.0,
   "amount": 76368000.0,
   "over_cap": false
  },
  {
   "code": "105560",
   "name": "KB금융",
   "weight": 1.5,
   "shares": 384.0,
   "amount": 71500800.0,
   "over_cap": false
  },
  {
   "code": "055550",
   "name": "신한지주",
   "weight": 1.18,
   "shares": 519.0,
   "amount": 56363400.0,
   "over_cap": false
  },
  {
   "code": "000270",
   "name": "기아",
   "weight": 0.93,
   "shares": 308.0,
   "amount": 44198000.0,
   "over_cap": false
  },
  {
   "code": "028260",
   "name": "삼성물산",
   "weight": 0.92,
   "shares": 122.0,
   "amount": 44042000.0,
   "over_cap": false
  },
  {
   "code": "086790",
   "name": "하나금융지주",
   "weight": 0.87,
   "shares": 314.0,
   "amount": 41636400.0,
   "over_cap": false
  },
  {
   "code": "034020",
   "name": "두산에너빌리티",
   "weight": 0.84,
   "shares": 546.0,
   "amount": 39967200.0,
   "over_cap": false
  },
  {
   "code": "012330",
   "name": "현대모비스",
   "weight": 0.81,
   "shares": 79.0,
   "amount": 38512500.0,
   "over_cap": false
  },
  {
   "code": "012450",
   "name": "한화에어로스페이스",
   "weight": 0.8,
   "shares": 41.0,
   "amount": 38376000.0,
   "over_cap": false
  },
  {
   "code": "032830",
   "name": "삼성생명",
   "weight": 0.73,
   "shares": 107.0,
   "amount": 34882000.0,
   "over_cap": false
  },
  {
   "code": "068270",
   "name": "셀트리온",
   "weight": 0.73,
   "shares": 198.0,
   "amount": 34669800.0,
   "over_cap": false
  },
  {
   "code": "006400",
   "name": "삼성SDI",
   "weight": 0.71,
   "shares": 77.0,
   "amount": 33880000.0,
   "over_cap": false
  },
  {
   "code": "035420",
   "name": "NAVER",
   "weight": 0.68,
   "shares": 174.0,
   "amount": 32712000.0,
   "over_cap": false
  },
  {
   "code": "316140",
   "name": "우리금융지주",
   "weight": 0.56,
   "shares": 850.0,
   "amount": 26520000.0,
   "over_cap": false
  },
  {
   "code": "005490",
   "name": "POSCO홀딩스",
   "weight": 0.55,
   "shares": 86.0,
   "amount": 26488000.0,
   "over_cap": false
  },
  {
   "code": "034730",
   "name": "SK",
   "weight": 0.55,
   "shares": 45.0,
   "amount": 26235000.0,
   "over_cap": false
  },
  {
   "code": "066570",
   "name": "LG전자",
   "weight": 0.53,
   "shares": 137.0,
   "amount": 25427200.0,
   "over_cap": false
  },
  {
   "code": "000810",
   "name": "삼성화재",
   "weight": 0.49,
   "shares": 37.0,
   "amount": 23643000.0,
   "over_cap": false
  },
  {
   "code": "267260",
   "name": "HD현대일렉트릭",
   "weight": 0.46,
   "shares": 28.0,
   "amount": 22064000.0,
   "over_cap": false
  },
  {
   "code": "373220",
   "name": "LG에너지솔루션",
   "weight": 0.43,
   "shares": 63.0,
   "amount": 20695500.0,
   "over_cap": false
  },
  {
   "code": "009540",
   "name": "HD한국조선해양",
   "weight": 0.42,
   "shares": 59.0,
   "amount": 20148500.0,
   "over_cap": false
  },
  {
   "code": "329180",
   "name": "HD현대중공업",
   "weight": 0.42,
   "shares": 41.0,
   "amount": 19987500.0,
   "over_cap": false
  },
  {
   "code": "033780",
   "name": "KT&G",
   "weight": 0.42,
   "shares": 114.0,
   "amount": 19870200.0,
   "over_cap": false
  },
  {
   "code": "010140",
   "name": "삼성중공업",
   "weight": 0.39,
   "shares": 840.0,
   "amount": 18522000.0,
   "over_cap": false
  },
  {
   "code": "010120",
   "name": "LS ELECTRIC",
   "weight": 0.38,
   "shares": 99.0,
   "amount": 18265500.0,
   "over_cap": false
  },
  {
   "code": "207940",
   "name": "삼성바이오로직스",
   "weight": 0.38,
   "shares": 13.0,
   "amount": 18200000.0,
   "over_cap": false
  },
  {
   "code": "196170",
   "name": "알테오젠",
   "weight": 0.34,
   "shares": 52.0,
   "amount": 16458000.0,
   "over_cap": false
  },
  {
   "code": "017670",
   "name": "SK텔레콤",
   "weight": 0.34,
   "shares": 189.0,
   "amount": 16197300.0,
   "over_cap": false
  },
  {
   "code": "298040",
   "name": "효성중공업",
   "weight": 0.33,
   "shares": 6.0,
   "amount": 15996000.0,
   "over_cap": false
  },
  {
   "code": "064350",
   "name": "현대로템",
   "weight": 0.33,
   "shares": 93.0,
   "amount": 15810000.0,
   "over_cap": false
  },
  {
   "code": "051910",
   "name": "LG화학",
   "weight": 0.32,
   "shares": 58.0,
   "amount": 15109000.0,
   "over_cap": false
  },
  {
   "code": "035720",
   "name": "카카오",
   "weight": 0.31,
   "shares": 427.0,
   "amount": 14838250.0,
   "over_cap": false
  },
  {
   "code": "030200",
   "name": "KT",
   "weight": 0.31,
   "shares": 279.0,
   "amount": 14703300.0,
   "over_cap": false
  },
  {
   "code": "015760",
   "name": "한국전력",
   "weight": 0.29,
   "shares": 400.0,
   "amount": 13700000.0,
   "over_cap": false
  },
  {
   "code": "006800",
   "name": "미래에셋증권",
   "weight": 0.29,
   "shares": 342.0,
   "amount": 13680000.0,
   "over_cap": false
  },
  {
   "code": "042660",
   "name": "한화오션",
   "weight": 0.28,
   "shares": 168.0,
   "amount": 13238400.0,
   "over_cap": false
  },
  {
   "code": "047810",
   "name": "한국항공우주",
   "weight": 0.27,
   "shares": 89.0,
   "amount": 12771500.0,
   "over_cap": false
  },
  {
   "code": "079550",
   "name": "LIG디펜스앤에어로스페이스",
   "weight": 0.26,
   "shares": 17.0,
   "amount": 12325000.0,
   "over_cap": false
  },
  {
   "code": "071050",
   "name": "한국금융지주",
   "weight": 0.26,
   "shares": 52.0,
   "amount": 12324000.0,
   "over_cap": false
  },
  {
   "code": "011070",
   "name": "LG이노텍",
   "weight": 0.25,
   "shares": 18.0,
   "amount": 11898000.0,
   "over_cap": false
  },
  {
   "code": "278470",
   "name": "에이피알",
   "weight": 0.25,
   "shares": 31.0,
   "amount": 11780000.0,
   "over_cap": false
  },
  {
   "code": "003550",
   "name": "LG",
   "weight": 0.24,
   "shares": 114.0,
   "amount": 11320200.0,
   "over_cap": false
  },
  {
   "code": "267250",
   "name": "HD현대",
   "weight": 0.24,
   "shares": 57.0,
   "amount": 11286000.0,
   "over_cap": false
  },
  {
   "code": "000150",
   "name": "두산",
   "weight": 0.23,
   "shares": 9.0,
   "amount": 11142000.0,
   "over_cap": false
  },
  {
   "code": "138040",
   "name": "메리츠금융지주",
   "weight": 0.23,
   "shares": 94.0,
   "amount": 10998000.0,
   "over_cap": false
  },
  {
   "code": "042700",
   "name": "한미반도체",
   "weight": 0.23,
   "shares": 53.0,
   "amount": 10891500.0,
   "over_cap": false
  },
  {
   "code": "096770",
   "name": "SK이노베이션",
   "weight": 0.22,
   "shares": 95.0,
   "amount": 10469000.0,
   "over_cap": false
  },
  {
   "code": "086520",
   "name": "에코프로",
   "weight": 0.22,
   "shares": 124.0,
   "amount": 10366400.0,
   "over_cap": false
  },
  {
   "code": "010130",
   "name": "고려아연",
   "weight": 0.21,
   "shares": 10.0,
   "amount": 10250000.0,
   "over_cap": false
  },
  {
   "code": "323410",
   "name": "카카오뱅크",
   "weight": 0.21,
   "shares": 431.0,
   "amount": 10042300.0,
   "over_cap": false
  },
  {
   "code": "000720",
   "name": "현대건설",
   "weight": 0.2,
   "shares": 94.0,
   "amount": 9541000.0,
   "over_cap": false
  },
  {
   "code": "018260",
   "name": "삼성에스디에스",
   "weight": 0.19,
   "shares": 48.0,
   "amount": 9129600.0,
   "over_cap": false
  },
  {
   "code": "086280",
   "name": "현대글로비스",
   "weight": 0.18,
   "shares": 47.0,
   "amount": 8826600.0,
   "over_cap": false
  },
  {
   "code": "259960",
   "name": "크래프톤",
   "weight": 0.18,
   "shares": 36.0,
   "amount": 8568000.0,
   "over_cap": false
  },
  {
   "code": "016360",
   "name": "삼성증권",
   "weight": 0.18,
   "shares": 77.0,
   "amount": 8377600.0,
   "over_cap": false
  },
  {
   "code": "003490",
   "name": "대한항공",
   "weight": 0.17,
   "shares": 323.0,
   "amount": 8349550.0,
   "over_cap": false
  },
  {
   "code": "005830",
   "name": "DB손해보험",
   "weight": 0.17,
   "shares": 52.0,
   "amount": 8273200.0,
   "over_cap": false
  },
  {
   "code": "028050",
   "name": "삼성E&A",
   "weight": 0.17,
   "shares": 200.0,
   "amount": 8220000.0,
   "over_cap": false
  },
  {
   "code": "247540",
   "name": "에코프로비엠",
   "weight": 0.17,
   "shares": 68.0,
   "amount": 8146400.0,
   "over_cap": false
  },
  {
   "code": "180640",
   "name": "한진칼",
   "weight": 0.16,
   "shares": 59.0,
   "amount": 7764400.0,
   "over_cap": false
  },
  {
   "code": "011200",
   "name": "HMM",
   "weight": 0.16,
   "shares": 396.0,
   "amount": 7741800.0,
   "over_cap": false
  },
  {
   "code": "010950",
   "name": "S-Oil",
   "weight": 0.15,
   "shares": 53.0,
   "amount": 7393500.0,
   "over_cap": false
  },
  {
   "code": "036930",
   "name": "주성엔지니어링",
   "weight": 0.15,
   "shares": 40.0,
   "amount": 7300000.0,
   "over_cap": false
  },
  {
   "code": "024110",
   "name": "기업은행",
   "weight": 0.15,
   "shares": 345.0,
   "amount": 7296750.0,
   "over_cap": false
  },
  {
   "code": "007660",
   "name": "이수페타시스",
   "weight": 0.14,
   "shares": 69.0,
   "amount": 6872400.0,
   "over_cap": false
  },
  {
   "code": "352820",
   "name": "하이브",
   "weight": 0.14,
   "shares": 32.0,
   "amount": 6816000.0,
   "over_cap": false
  },
  {
   "code": "003670",
   "name": "포스코퓨처엠",
   "weight": 0.14,
   "shares": 45.0,
   "amount": 6781500.0,
   "over_cap": false
  },
  {
   "code": "039490",
   "name": "키움증권",
   "weight": 0.14,
   "shares": 20.0,
   "amount": 6470000.0,
   "over_cap": false
  },
  {
   "code": "006260",
   "name": "LS",
   "weight": 0.13,
   "shares": 21.0,
   "amount": 6373500.0,
   "over_cap": false
  },
  {
   "code": "161390",
   "name": "한국타이어앤테크놀로지",
   "weight": 0.13,
   "shares": 91.0,
   "amount": 6342700.0,
   "over_cap": false
  },
  {
   "code": "138930",
   "name": "BNK금융지주",
   "weight": 0.13,
   "shares": 344.0,
   "amount": 6247040.0,
   "over_cap": false
  },
  {
   "code": "021240",
   "name": "코웨이",
   "weight": 0.13,
   "shares": 68.0,
   "amount": 6235600.0,
   "over_cap": false
  },
  {
   "code": "272210",
   "name": "한화시스템",
   "weight": 0.12,
   "shares": 89.0,
   "amount": 5918500.0,
   "over_cap": false
  },
  {
   "code": "005940",
   "name": "NH투자증권",
   "weight": 0.12,
   "shares": 186.0,
   "amount": 5793900.0,
   "over_cap": false
  },
  {
   "code": "175330",
   "name": "JB금융지주",
   "weight": 0.12,
   "shares": 199.0,
   "amount": 5572000.0,
   "over_cap": false
  },
  {
   "code": "003230",
   "name": "삼양식품",
   "weight": 0.12,
   "shares": 5.0,
   "amount": 5550000.0,
   "over_cap": false
  },
  {
   "code": "009830",
   "name": "한화솔루션",
   "weight": 0.12,
   "shares": 172.0,
   "amount": 5504000.0,
   "over_cap": false
  },
  {
   "code": "036570",
   "name": "NC",
   "weight": 0.11,
   "shares": 22.0,
   "amount": 5291000.0,
   "over_cap": false
  },
  {
   "code": "240810",
   "name": "원익IPS",
   "weight": 0.11,
   "shares": 42.0,
   "amount": 5241600.0,
   "over_cap": false
  },
  {
   "code": "000100",
   "name": "유한양행",
   "weight": 0.11,
   "shares": 76.0,
   "amount": 5175600.0,
   "over_cap": false
  },
  {
   "code": "032640",
   "name": "LG유플러스",
   "weight": 0.11,
   "shares": 346.0,
   "amount": 5027380.0,
   "over_cap": false
  },
  {
   "code": "443060",
   "name": "HD현대마린솔루션",
   "weight": 0.1,
   "shares": 25.0,
   "amount": 4840000.0,
   "over_cap": false
  },
  {
   "code": "090430",
   "name": "아모레퍼시픽",
   "weight": 0.1,
   "shares": 39.0,
   "amount": 4742400.0,
   "over_cap": false
  },
  {
   "code": "004170",
   "name": "신세계",
   "weight": 0.1,
   "shares": 8.0,
   "amount": 4728000.0,
   "over_cap": false
  },
  {
   "code": "353200",
   "name": "대덕전자",
   "weight": 0.1,
   "shares": 41.0,
   "amount": 4665800.0,
   "over_cap": false
  },
  {
   "code": "319660",
   "name": "피에스케이",
   "weight": 0.1,
   "shares": 25.0,
   "amount": 4615000.0,
   "over_cap": false
  },
  {
   "code": "267270",
   "name": "HD건설기계",
   "weight": 0.1,
   "shares": 36.0,
   "amount": 4572000.0,
   "over_cap": false
  },
  {
   "code": "058470",
   "name": "리노공업",
   "weight": 0.1,
   "shares": 63.0,
   "amount": 4554900.0,
   "over_cap": false
  },
  {
   "code": "078930",
   "name": "GS",
   "weight": 0.09,
   "shares": 57.0,
   "amount": 4531500.0,
   "over_cap": false
  },
  {
   "code": "000990",
   "name": "DB하이텍",
   "weight": 0.09,
   "shares": 39.0,
   "amount": 4317300.0,
   "over_cap": false
  },
  {
   "code": "001440",
   "name": "대한전선",
   "weight": 0.09,
   "shares": 150.0,
   "amount": 4245000.0,
   "over_cap": false
  },
  {
   "code": "298380",
   "name": "에이비엘바이오",
   "weight": 0.09,
   "shares": 53.0,
   "amount": 4192300.0,
   "over_cap": false
  },
  {
   "code": "034220",
   "name": "LG디스플레이",
   "weight": 0.09,
   "shares": 401.0,
   "amount": 4154360.0,
   "over_cap": false
  },
  {
   "code": "277810",
   "name": "레인보우로보틱스",
   "weight": 0.09,
   "shares": 10.0,
   "amount": 4150000.0,
   "over_cap": false
  },
  {
   "code": "064400",
   "name": "LG씨엔에스",
   "weight": 0.09,
   "shares": 60.0,
   "amount": 4092000.0,
   "over_cap": false
  },
  {
   "code": "241560",
   "name": "두산밥캣",
   "weight": 0.09,
   "shares": 66.0,
   "amount": 4065600.0,
   "over_cap": false
  },
  {
   "code": "047040",
   "name": "대우건설",
   "weight": 0.08,
   "shares": 251.0,
   "amount": 4018510.0,
   "over_cap": false
  },
  {
   "code": "326030",
   "name": "SK바이오팜",
   "weight": 0.08,
   "shares": 50.0,
   "amount": 3965000.0,
   "over_cap": false
  },
  {
   "code": "039030",
   "name": "이오테크닉스",
   "weight": 0.08,
   "shares": 11.0,
   "amount": 3954500.0,
   "over_cap": false
  },
  {
   "code": "066970",
   "name": "엘앤에프",
   "weight": 0.08,
   "shares": 39.0,
   "amount": 3950700.0,
   "over_cap": false
  },
  {
   "code": "028300",
   "name": "HLB",
   "weight": 0.08,
   "shares": 149.0,
   "amount": 3821850.0,
   "over_cap": false
  },
  {
   "code": "271560",
   "name": "오리온",
   "weight": 0.08,
   "shares": 28.0,
   "amount": 3743600.0,
   "over_cap": false
  },
  {
   "code": "141080",
   "name": "리가켐바이오",
   "weight": 0.08,
   "shares": 33.0,
   "amount": 3738900.0,
   "over_cap": false
  },
  {
   "code": "062040",
   "name": "산일전기",
   "weight": 0.07,
   "shares": 21.0,
   "amount": 3565800.0,
   "over_cap": false
  },
  {
   "code": "307950",
   "name": "현대오토에버",
   "weight": 0.07,
   "shares": 8.0,
   "amount": 3504000.0,
   "over_cap": false
  },
  {
   "code": "403870",
   "name": "HPSP",
   "weight": 0.07,
   "shares": 83.0,
   "amount": 3477700.0,
   "over_cap": false
  },
  {
   "code": "010060",
   "name": "OCI홀딩스",
   "weight": 0.07,
   "shares": 17.0,
   "amount": 3476500.0,
   "over_cap": false
  },
  {
   "code": "347850",
   "name": "디앤디파마텍",
   "weight": 0.07,
   "shares": 44.0,
   "amount": 3388000.0,
   "over_cap": false
  },
  {
   "code": "014680",
   "name": "한솔케미칼",
   "weight": 0.07,
   "shares": 13.0,
   "amount": 3380000.0,
   "over_cap": false
  },
  {
   "code": "222800",
   "name": "심텍",
   "weight": 0.07,
   "shares": 31.0,
   "amount": 3351100.0,
   "over_cap": false
  },
  {
   "code": "000250",
   "name": "삼천당제약",
   "weight": 0.07,
   "shares": 18.0,
   "amount": 3328200.0,
   "over_cap": false
  },
  {
   "code": "139130",
   "name": "iM금융지주",
   "weight": 0.07,
   "shares": 176.0,
   "amount": 3206720.0,
   "over_cap": false
  },
  {
   "code": "082740",
   "name": "한화엔진",
   "weight": 0.07,
   "shares": 69.0,
   "amount": 3187800.0,
   "over_cap": false
  },
  {
   "code": "128940",
   "name": "한미약품",
   "weight": 0.06,
   "shares": 8.0,
   "amount": 3052000.0,
   "over_cap": false
  },
  {
   "code": "000880",
   "name": "한화",
   "weight": 0.06,
   "shares": 33.0,
   "amount": 3045900.0,
   "over_cap": false
  },
  {
   "code": "080220",
   "name": "제주반도체",
   "weight": 0.06,
   "shares": 39.0,
   "amount": 3014700.0,
   "over_cap": false
  },
  {
   "code": "051900",
   "name": "LG생활건강",
   "weight": 0.06,
   "shares": 12.0,
   "amount": 2982000.0,
   "over_cap": false
  },
  {
   "code": "214450",
   "name": "파마리서치",
   "weight": 0.06,
   "shares": 9.0,
   "amount": 2974500.0,
   "over_cap": false
  },
  {
   "code": "454910",
   "name": "두산로보틱스",
   "weight": 0.06,
   "shares": 42.0,
   "amount": 2944200.0,
   "over_cap": false
  },
  {
   "code": "047050",
   "name": "포스코인터내셔널",
   "weight": 0.06,
   "shares": 58.0,
   "amount": 2934800.0,
   "over_cap": false
  },
  {
   "code": "087010",
   "name": "펩트론",
   "weight": 0.06,
   "shares": 27.0,
   "amount": 2921400.0,
   "over_cap": false
  },
  {
   "code": "011790",
   "name": "SKC",
   "weight": 0.06,
   "shares": 33.0,
   "amount": 2904000.0,
   "over_cap": false
  },
  {
   "code": "108490",
   "name": "로보티즈",
   "weight": 0.06,
   "shares": 14.0,
   "amount": 2884000.0,
   "over_cap": false
  },
  {
   "code": "004020",
   "name": "현대제철",
   "weight": 0.06,
   "shares": 107.0,
   "amount": 2867600.0,
   "over_cap": false
  },
  {
   "code": "001450",
   "name": "현대해상",
   "weight": 0.06,
   "shares": 73.0,
   "amount": 2814150.0,
   "over_cap": false
  },
  {
   "code": "095610",
   "name": "테스",
   "weight": 0.06,
   "shares": 15.0,
   "amount": 2796000.0,
   "over_cap": false
  },
  {
   "code": "226950",
   "name": "올릭스",
   "weight": 0.06,
   "shares": 21.0,
   "amount": 2677500.0,
   "over_cap": false
  },
  {
   "code": "0126Z0",
   "name": "삼성에피스홀딩스",
   "weight": 0.06,
   "shares": 7.0,
   "amount": 2646000.0,
   "over_cap": false
  },
  {
   "code": "084370",
   "name": "유진테크",
   "weight": 0.05,
   "shares": 17.0,
   "amount": 2602700.0,
   "over_cap": false
  },
  {
   "code": "483650",
   "name": "달바글로벌",
   "weight": 0.05,
   "shares": 13.0,
   "amount": 2593500.0,
   "over_cap": false
  },
  {
   "code": "161890",
   "name": "한국콜마",
   "weight": 0.05,
   "shares": 22.0,
   "amount": 2547600.0,
   "over_cap": false
  },
  {
   "code": "009420",
   "name": "한올바이오파마",
   "weight": 0.05,
   "shares": 45.0,
   "amount": 2484000.0,
   "over_cap": false
  },
  {
   "code": "178320",
   "name": "서진시스템",
   "weight": 0.05,
   "shares": 62.0,
   "amount": 2433500.0,
   "over_cap": false
  },
  {
   "code": "001040",
   "name": "CJ",
   "weight": 0.05,
   "shares": 17.0,
   "amount": 2424200.0,
   "over_cap": false
  },
  {
   "code": "006360",
   "name": "GS건설",
   "weight": 0.05,
   "shares": 82.0,
   "amount": 2414900.0,
   "over_cap": false
  },
  {
   "code": "003690",
   "name": "코리안리",
   "weight": 0.05,
   "shares": 171.0,
   "amount": 2382030.0,
   "over_cap": false
  },
  {
   "code": "111770",
   "name": "영원무역",
   "weight": 0.05,
   "shares": 28.0,
   "amount": 2368800.0,
   "over_cap": false
  },
  {
   "code": "069960",
   "name": "현대백화점",
   "weight": 0.05,
   "shares": 15.0,
   "amount": 2368500.0,
   "over_cap": false
  },
  {
   "code": "052690",
   "name": "한전기술",
   "weight": 0.05,
   "shares": 24.0,
   "amount": 2342400.0,
   "over_cap": false
  },
  {
   "code": "067310",
   "name": "하나마이크론",
   "weight": 0.05,
   "shares": 61.0,
   "amount": 2330200.0,
   "over_cap": false
  },
  {
   "code": "336260",
   "name": "두산퓨얼셀",
   "weight": 0.05,
   "shares": 51.0,
   "amount": 2284800.0,
   "over_cap": false
  },
  {
   "code": "375500",
   "name": "DL이앤씨",
   "weight": 0.05,
   "shares": 37.0,
   "amount": 2231100.0,
   "over_cap": false
  },
  {
   "code": "011780",
   "name": "금호석유화학",
   "weight": 0.05,
   "shares": 19.0,
   "amount": 2230600.0,
   "over_cap": false
  },
  {
   "code": "017800",
   "name": "현대엘리베이터",
   "weight": 0.05,
   "shares": 32.0,
   "amount": 2198400.0,
   "over_cap": false
  },
  {
   "code": "002380",
   "name": "KCC",
   "weight": 0.05,
   "shares": 5.0,
   "amount": 2170000.0,
   "over_cap": false
  },
  {
   "code": "032820",
   "name": "우리기술",
   "weight": 0.04,
   "shares": 201.0,
   "amount": 2148690.0,
   "over_cap": false
  },
  {
   "code": "035250",
   "name": "강원랜드",
   "weight": 0.04,
   "shares": 144.0,
   "amount": 2113920.0,
   "over_cap": false
  },
  {
   "code": "310210",
   "name": "보로노이",
   "weight": 0.04,
   "shares": 14.0,
   "amount": 2087400.0,
   "over_cap": false
  },
  {
   "code": "103590",
   "name": "일진전기",
   "weight": 0.04,
   "shares": 34.0,
   "amount": 2074000.0,
   "over_cap": false
  },
  {
   "code": "139480",
   "name": "이마트",
   "weight": 0.04,
   "shares": 25.0,
   "amount": 2057500.0,
   "over_cap": false
  },
  {
   "code": "237690",
   "name": "에스티팜",
   "weight": 0.04,
   "shares": 16.0,
   "amount": 2014400.0,
   "over_cap": false
  },
  {
   "code": "023530",
   "name": "롯데쇼핑",
   "weight": 0.04,
   "shares": 13.0,
   "amount": 2005900.0,
   "over_cap": false
  },
  {
   "code": "095340",
   "name": "ISC",
   "weight": 0.04,
   "shares": 13.0,
   "amount": 1995500.0,
   "over_cap": false
  },
  {
   "code": "204320",
   "name": "HL만도",
   "weight": 0.04,
   "shares": 41.0,
   "amount": 1951600.0,
   "over_cap": false
  },
  {
   "code": "008770",
   "name": "호텔신라",
   "weight": 0.04,
   "shares": 39.0,
   "amount": 1940250.0,
   "over_cap": false
  },
  {
   "code": "005290",
   "name": "동진쎄미켐",
   "weight": 0.04,
   "shares": 43.0,
   "amount": 1926400.0,
   "over_cap": false
  },
  {
   "code": "097950",
   "name": "CJ제일제당",
   "weight": 0.04,
   "shares": 10.0,
   "amount": 1919000.0,
   "over_cap": false
  },
  {
   "code": "489790",
   "name": "한화비전",
   "weight": 0.04,
   "shares": 44.0,
   "amount": 1914000.0,
   "over_cap": false
  },
  {
   "code": "192820",
   "name": "코스맥스",
   "weight": 0.04,
   "shares": 10.0,
   "amount": 1843000.0,
   "over_cap": false
  },
  {
   "code": "088350",
   "name": "한화생명",
   "weight": 0.04,
   "shares": 420.0,
   "amount": 1829100.0,
   "over_cap": false
  },
  {
   "code": "377300",
   "name": "카카오페이",
   "weight": 0.04,
   "shares": 46.0,
   "amount": 1828500.0,
   "over_cap": false
  },
  {
   "code": "450080",
   "name": "에코프로머티",
   "weight": 0.04,
   "shares": 49.0,
   "amount": 1820350.0,
   "over_cap": false
  },
  {
   "code": "081660",
   "name": "미스토홀딩스",
   "weight": 0.04,
   "shares": 39.0,
   "amount": 1760850.0,
   "over_cap": false
  },
  {
   "code": "214150",
   "name": "클래시스",
   "weight": 0.04,
   "shares": 37.0,
   "amount": 1755650.0,
   "over_cap": false
  },
  {
   "code": "257720",
   "name": "실리콘투",
   "weight": 0.04,
   "shares": 45.0,
   "amount": 1725750.0,
   "over_cap": false
  },
  {
   "code": "145020",
   "name": "휴젤",
   "weight": 0.04,
   "shares": 7.0,
   "amount": 1715000.0,
   "over_cap": false
  },
  {
   "code": "098460",
   "name": "고영",
   "weight": 0.04,
   "shares": 66.0,
   "amount": 1706100.0,
   "over_cap": false
  },
  {
   "code": "035900",
   "name": "JYP Ent.",
   "weight": 0.04,
   "shares": 34.0,
   "amount": 1688100.0,
   "over_cap": false
  },
  {
   "code": "263750",
   "name": "펄어비스",
   "weight": 0.04,
   "shares": 48.0,
   "amount": 1684800.0,
   "over_cap": false
  },
  {
   "code": "071970",
   "name": "HD현대마린엔진",
   "weight": 0.03,
   "shares": 28.0,
   "amount": 1668800.0,
   "over_cap": false
  },
  {
   "code": "290650",
   "name": "엘앤씨바이오",
   "weight": 0.03,
   "shares": 24.0,
   "amount": 1668000.0,
   "over_cap": false
  },
  {
   "code": "030000",
   "name": "제일기획",
   "weight": 0.03,
   "shares": 88.0,
   "amount": 1650880.0,
   "over_cap": false
  },
  {
   "code": "029780",
   "name": "삼성카드",
   "weight": 0.03,
   "shares": 34.0,
   "amount": 1625200.0,
   "over_cap": false
  },
  {
   "code": "064760",
   "name": "티씨케이",
   "weight": 0.03,
   "shares": 7.0,
   "amount": 1606500.0,
   "over_cap": false
  },
  {
   "code": "457190",
   "name": "이수스페셜티케미컬",
   "weight": 0.03,
   "shares": 26.0,
   "amount": 1586000.0,
   "over_cap": false
  },
  {
   "code": "357780",
   "name": "솔브레인",
   "weight": 0.03,
   "shares": 5.0,
   "amount": 1542500.0,
   "over_cap": false
  },
  {
   "code": "036460",
   "name": "한국가스공사",
   "weight": 0.03,
   "shares": 47.0,
   "amount": 1536900.0,
   "over_cap": false
  },
  {
   "code": "018880",
   "name": "한온시스템",
   "weight": 0.03,
   "shares": 444.0,
   "amount": 1527360.0,
   "over_cap": false
  },
  {
   "code": "140860",
   "name": "파크시스템스",
   "weight": 0.03,
   "shares": 6.0,
   "amount": 1524000.0,
   "over_cap": false
  },
  {
   "code": "007390",
   "name": "네이처셀",
   "weight": 0.03,
   "shares": 65.0,
   "amount": 1521000.0,
   "over_cap": false
  },
  {
   "code": "319400",
   "name": "현대무벡스",
   "weight": 0.03,
   "shares": 71.0,
   "amount": 1515850.0,
   "over_cap": false
  },
  {
   "code": "028670",
   "name": "팬오션",
   "weight": 0.03,
   "shares": 286.0,
   "amount": 1498640.0,
   "over_cap": false
  },
  {
   "code": "089030",
   "name": "테크윙",
   "weight": 0.03,
   "shares": 34.0,
   "amount": 1490900.0,
   "over_cap": false
  },
  {
   "code": "251270",
   "name": "넷마블",
   "weight": 0.03,
   "shares": 39.0,
   "amount": 1487850.0,
   "over_cap": false
  },
  {
   "code": "383220",
   "name": "F&F",
   "weight": 0.03,
   "shares": 18.0,
   "amount": 1438200.0,
   "over_cap": false
  },
  {
   "code": "004370",
   "name": "농심",
   "weight": 0.03,
   "shares": 4.0,
   "amount": 1424000.0,
   "over_cap": false
  },
  {
   "code": "282330",
   "name": "BGF리테일",
   "weight": 0.03,
   "shares": 11.0,
   "amount": 1405800.0,
   "over_cap": false
  },
  {
   "code": "011170",
   "name": "롯데케미칼",
   "weight": 0.03,
   "shares": 23.0,
   "amount": 1393800.0,
   "over_cap": false
  },
  {
   "code": "131970",
   "name": "두산테스나",
   "weight": 0.03,
   "shares": 15.0,
   "amount": 1387500.0,
   "over_cap": false
  },
  {
   "code": "120110",
   "name": "코오롱인더",
   "weight": 0.03,
   "shares": 25.0,
   "amount": 1335000.0,
   "over_cap": false
  },
  {
   "code": "103140",
   "name": "풍산",
   "weight": 0.03,
   "shares": 21.0,
   "amount": 1318800.0,
   "over_cap": false
  },
  {
   "code": "112610",
   "name": "씨에스윈드",
   "weight": 0.03,
   "shares": 31.0,
   "amount": 1283400.0,
   "over_cap": false
  },
  {
   "code": "041510",
   "name": "에스엠",
   "weight": 0.03,
   "shares": 17.0,
   "amount": 1273300.0,
   "over_cap": false
  },
  {
   "code": "214370",
   "name": "케어젠",
   "weight": 0.03,
   "shares": 20.0,
   "amount": 1272000.0,
   "over_cap": false
  },
  {
   "code": "031980",
   "name": "피에스케이홀딩스",
   "weight": 0.03,
   "shares": 9.0,
   "amount": 1260900.0,
   "over_cap": false
  },
  {
   "code": "083650",
   "name": "비에이치아이",
   "weight": 0.03,
   "shares": 27.0,
   "amount": 1251450.0,
   "over_cap": false
  },
  {
   "code": "039200",
   "name": "오스코텍",
   "weight": 0.03,
   "shares": 42.0,
   "amount": 1239000.0,
   "over_cap": false
  },
  {
   "code": "051600",
   "name": "한전KPS",
   "weight": 0.03,
   "shares": 28.0,
   "amount": 1233400.0,
   "over_cap": false
  },
  {
   "code": "020150",
   "name": "롯데에너지머티리얼즈",
   "weight": 0.03,
   "shares": 36.0,
   "amount": 1218600.0,
   "over_cap": false
  },
  {
   "code": "475150",
   "name": "SK이터닉스",
   "weight": 0.03,
   "shares": 25.0,
   "amount": 1201250.0,
   "over_cap": false
  },
  {
   "code": "022100",
   "name": "포스코DX",
   "weight": 0.03,
   "shares": 64.0,
   "amount": 1199360.0,
   "over_cap": false
  },
  {
   "code": "011210",
   "name": "현대위아",
   "weight": 0.03,
   "shares": 20.0,
   "amount": 1198000.0,
   "over_cap": false
  },
  {
   "code": "302440",
   "name": "SK바이오사이언스",
   "weight": 0.03,
   "shares": 33.0,
   "amount": 1197900.0,
   "over_cap": false
  },
  {
   "code": "183300",
   "name": "코미코",
   "weight": 0.02,
   "shares": 15.0,
   "amount": 1194000.0,
   "over_cap": false
  },
  {
   "code": "008930",
   "name": "한미사이언스",
   "weight": 0.02,
   "shares": 36.0,
   "amount": 1191600.0,
   "over_cap": false
  },
  {
   "code": "058610",
   "name": "에스피지",
   "weight": 0.02,
   "shares": 17.0,
   "amount": 1171300.0,
   "over_cap": false
  },
  {
   "code": "439260",
   "name": "대한조선",
   "weight": 0.02,
   "shares": 25.0,
   "amount": 1161250.0,
   "over_cap": false
  },
  {
   "code": "009970",
   "name": "영원무역홀딩스",
   "weight": 0.02,
   "shares": 6.0,
   "amount": 1158600.0,
   "over_cap": false
  },
  {
   "code": "005070",
   "name": "코스모신소재",
   "weight": 0.02,
   "shares": 30.0,
   "amount": 1156500.0,
   "over_cap": false
  },
  {
   "code": "007070",
   "name": "GS리테일",
   "weight": 0.02,
   "shares": 43.0,
   "amount": 1143800.0,
   "over_cap": false
  },
  {
   "code": "078600",
   "name": "대주전자재료",
   "weight": 0.02,
   "shares": 14.0,
   "amount": 1134000.0,
   "over_cap": false
  },
  {
   "code": "458870",
   "name": "씨어스",
   "weight": 0.02,
   "shares": 34.0,
   "amount": 1120300.0,
   "over_cap": false
  },
  {
   "code": "096530",
   "name": "씨젠",
   "weight": 0.02,
   "shares": 39.0,
   "amount": 1109550.0,
   "over_cap": false
  },
  {
   "code": "005850",
   "name": "에스엘",
   "weight": 0.02,
   "shares": 20.0,
   "amount": 1084000.0,
   "over_cap": false
  },
  {
   "code": "007810",
   "name": "코리아써키트",
   "weight": 0.02,
   "shares": 15.0,
   "amount": 1047000.0,
   "over_cap": false
  },
  {
   "code": "475830",
   "name": "오름테라퓨틱",
   "weight": 0.02,
   "shares": 23.0,
   "amount": 1044200.0,
   "over_cap": false
  },
  {
   "code": "000120",
   "name": "CJ대한통운",
   "weight": 0.02,
   "shares": 14.0,
   "amount": 1030400.0,
   "over_cap": false
  },
  {
   "code": "073240",
   "name": "금호타이어",
   "weight": 0.02,
   "shares": 143.0,
   "amount": 1023880.0,
   "over_cap": false
  },
  {
   "code": "082920",
   "name": "비츠로셀",
   "weight": 0.02,
   "shares": 35.0,
   "amount": 1013250.0,
   "over_cap": false
  },
  {
   "code": "017960",
   "name": "한국카본",
   "weight": 0.02,
   "shares": 41.0,
   "amount": 1008600.0,
   "over_cap": false
  },
  {
   "code": "068760",
   "name": "셀트리온제약",
   "weight": 0.02,
   "shares": 25.0,
   "amount": 1006250.0,
   "over_cap": false
  },
  {
   "code": "090710",
   "name": "휴림로봇",
   "weight": 0.02,
   "shares": 150.0,
   "amount": 1000500.0,
   "over_cap": false
  },
  {
   "code": "101490",
   "name": "에스앤에스텍",
   "weight": 0.02,
   "shares": 21.0,
   "amount": 990150.0,
   "over_cap": false
  },
  {
   "code": "218410",
   "name": "RFHIC",
   "weight": 0.02,
   "shares": 21.0,
   "amount": 990150.0,
   "over_cap": false
  },
  {
   "code": "007340",
   "name": "DN오토모티브",
   "weight": 0.02,
   "shares": 26.0,
   "amount": 985400.0,
   "over_cap": false
  },
  {
   "code": "097230",
   "name": "HJ중공업",
   "weight": 0.02,
   "shares": 60.0,
   "amount": 959400.0,
   "over_cap": false
  },
  {
   "code": "323280",
   "name": "태성",
   "weight": 0.02,
   "shares": 27.0,
   "amount": 943650.0,
   "over_cap": false
  },
  {
   "code": "032350",
   "name": "롯데관광개발",
   "weight": 0.02,
   "shares": 65.0,
   "amount": 941200.0,
   "over_cap": false
  },
  {
   "code": "001720",
   "name": "신영증권",
   "weight": 0.02,
   "shares": 6.0,
   "amount": 909000.0,
   "over_cap": false
  },
  {
   "code": "030530",
   "name": "원익홀딩스",
   "weight": 0.02,
   "shares": 51.0,
   "amount": 897600.0,
   "over_cap": false
  },
  {
   "code": "347700",
   "name": "스피어",
   "weight": 0.02,
   "shares": 45.0,
   "amount": 895050.0,
   "over_cap": false
  },
  {
   "code": "003540",
   "name": "대신증권",
   "weight": 0.02,
   "shares": 33.0,
   "amount": 866250.0,
   "over_cap": false
  },
  {
   "code": "006280",
   "name": "녹십자",
   "weight": 0.02,
   "shares": 7.0,
   "amount": 843500.0,
   "over_cap": false
  },
  {
   "code": "322000",
   "name": "HD현대에너지솔루션",
   "weight": 0.02,
   "shares": 7.0,
   "amount": 840000.0,
   "over_cap": false
  },
  {
   "code": "004990",
   "name": "롯데지주",
   "weight": 0.02,
   "shares": 36.0,
   "amount": 829800.0,
   "over_cap": false
  },
  {
   "code": "004000",
   "name": "롯데정밀화학",
   "weight": 0.02,
   "shares": 18.0,
   "amount": 828000.0,
   "over_cap": false
  },
  {
   "code": "085660",
   "name": "차바이오텍",
   "weight": 0.02,
   "shares": 85.0,
   "amount": 824500.0,
   "over_cap": false
  },
  {
   "code": "298020",
   "name": "효성티앤씨",
   "weight": 0.02,
   "shares": 3.0,
   "amount": 816000.0,
   "over_cap": false
  },
  {
   "code": "328130",
   "name": "루닛",
   "weight": 0.02,
   "shares": 81.0,
   "amount": 802710.0,
   "over_cap": false
  },
  {
   "code": "069620",
   "name": "대웅제약",
   "weight": 0.02,
   "shares": 6.0,
   "amount": 795000.0,
   "over_cap": false
  },
  {
   "code": "466100",
   "name": "클로봇",
   "weight": 0.02,
   "shares": 32.0,
   "amount": 784000.0,
   "over_cap": false
  },
  {
   "code": "445680",
   "name": "큐리옥스바이오시스템즈",
   "weight": 0.02,
   "shares": 18.0,
   "amount": 782100.0,
   "over_cap": false
  },
  {
   "code": "043260",
   "name": "성호전자",
   "weight": 0.02,
   "shares": 41.0,
   "amount": 776950.0,
   "over_cap": false
  },
  {
   "code": "031210",
   "name": "서울보증보험",
   "weight": 0.02,
   "shares": 18.0,
   "amount": 759600.0,
   "over_cap": false
  },
  {
   "code": "122870",
   "name": "와이지엔터테인먼트",
   "weight": 0.02,
   "shares": 18.0,
   "amount": 751500.0,
   "over_cap": false
  },
  {
   "code": "002790",
   "name": "아모레퍼시픽홀딩스",
   "weight": 0.02,
   "shares": 31.0,
   "amount": 744000.0,
   "over_cap": false
  },
  {
   "code": "000240",
   "name": "한국앤컴퍼니",
   "weight": 0.02,
   "shares": 30.0,
   "amount": 739500.0,
   "over_cap": false
  },
  {
   "code": "137400",
   "name": "피엔티",
   "weight": 0.02,
   "shares": 24.0,
   "amount": 734400.0,
   "over_cap": false
  },
  {
   "code": "115180",
   "name": "큐리언트",
   "weight": 0.01,
   "shares": 40.0,
   "amount": 716400.0,
   "over_cap": false
  },
  {
   "code": "166090",
   "name": "하나머티리얼즈",
   "weight": 0.01,
   "shares": 13.0,
   "amount": 709800.0,
   "over_cap": false
  },
  {
   "code": "195940",
   "name": "HK이노엔",
   "weight": 0.01,
   "shares": 18.0,
   "amount": 704700.0,
   "over_cap": false
  },
  {
   "code": "099320",
   "name": "쎄트렉아이",
   "weight": 0.01,
   "shares": 9.0,
   "amount": 702000.0,
   "over_cap": false
  },
  {
   "code": "001800",
   "name": "오리온홀딩스",
   "weight": 0.01,
   "shares": 26.0,
   "amount": 696800.0,
   "over_cap": false
  },
  {
   "code": "034230",
   "name": "파라다이스",
   "weight": 0.01,
   "shares": 55.0,
   "amount": 690250.0,
   "over_cap": false
  },
  {
   "code": "100090",
   "name": "SK오션플랜트",
   "weight": 0.01,
   "shares": 50.0,
   "amount": 669500.0,
   "over_cap": false
  },
  {
   "code": "065350",
   "name": "신성델타테크",
   "weight": 0.01,
   "shares": 23.0,
   "amount": 663550.0,
   "over_cap": false
  },
  {
   "code": "018670",
   "name": "SK가스",
   "weight": 0.01,
   "shares": 3.0,
   "amount": 658500.0,
   "over_cap": false
  },
  {
   "code": "000210",
   "name": "DL",
   "weight": 0.01,
   "shares": 14.0,
   "amount": 637700.0,
   "over_cap": false
  },
  {
   "code": "397030",
   "name": "에이프릴바이오",
   "weight": 0.01,
   "shares": 24.0,
   "amount": 621600.0,
   "over_cap": false
  },
  {
   "code": "003530",
   "name": "한화투자증권",
   "weight": 0.01,
   "shares": 137.0,
   "amount": 621295.0,
   "over_cap": false
  },
  {
   "code": "161580",
   "name": "필옵틱스",
   "weight": 0.01,
   "shares": 21.0,
   "amount": 610050.0,
   "over_cap": false
  },
  {
   "code": "358570",
   "name": "지아이이노베이션",
   "weight": 0.01,
   "shares": 77.0,
   "amount": 605220.0,
   "over_cap": false
  },
  {
   "code": "000080",
   "name": "하이트진로",
   "weight": 0.01,
   "shares": 39.0,
   "amount": 583440.0,
   "over_cap": false
  },
  {
   "code": "281740",
   "name": "레이크머티리얼즈",
   "weight": 0.01,
   "shares": 47.0,
   "amount": 578100.0,
   "over_cap": false
  },
  {
   "code": "417200",
   "name": "LS머트리얼즈",
   "weight": 0.01,
   "shares": 48.0,
   "amount": 576000.0,
   "over_cap": false
  },
  {
   "code": "003380",
   "name": "하림지주",
   "weight": 0.01,
   "shares": 56.0,
   "amount": 570640.0,
   "over_cap": false
  },
  {
   "code": "376900",
   "name": "로킷헬스케어",
   "weight": 0.01,
   "shares": 15.0,
   "amount": 550500.0,
   "over_cap": false
  },
  {
   "code": "348370",
   "name": "엔켐",
   "weight": 0.01,
   "shares": 25.0,
   "amount": 536250.0,
   "over_cap": false
  },
  {
   "code": "060370",
   "name": "LS마린솔루션",
   "weight": 0.01,
   "shares": 20.0,
   "amount": 536000.0,
   "over_cap": false
  },
  {
   "code": "229640",
   "name": "LS에코에너지",
   "weight": 0.01,
   "shares": 12.0,
   "amount": 514200.0,
   "over_cap": false
  },
  {
   "code": "077970",
   "name": "STX엔진",
   "weight": 0.01,
   "shares": 20.0,
   "amount": 510000.0,
   "over_cap": false
  },
  {
   "code": "456160",
   "name": "지투지바이오",
   "weight": 0.01,
   "shares": 16.0,
   "amount": 506400.0,
   "over_cap": false
  },
  {
   "code": "232140",
   "name": "와이씨",
   "weight": 0.01,
   "shares": 50.0,
   "amount": 504000.0,
   "over_cap": false
  },
  {
   "code": "174900",
   "name": "앱클론",
   "weight": 0.01,
   "shares": 22.0,
   "amount": 498300.0,
   "over_cap": false
  },
  {
   "code": "001430",
   "name": "세아베스틸지주",
   "weight": 0.01,
   "shares": 16.0,
   "amount": 484000.0,
   "over_cap": false
  },
  {
   "code": "036540",
   "name": "SFA반도체",
   "weight": 0.01,
   "shares": 94.0,
   "amount": 481280.0,
   "over_cap": false
  },
  {
   "code": "285130",
   "name": "SK케미칼",
   "weight": 0.01,
   "shares": 12.0,
   "amount": 478200.0,
   "over_cap": false
  },
  {
   "code": "035760",
   "name": "CJ ENM",
   "weight": 0.01,
   "shares": 15.0,
   "amount": 474750.0,
   "over_cap": false
  },
  {
   "code": "437730",
   "name": "삼현",
   "weight": 0.01,
   "shares": 15.0,
   "amount": 469500.0,
   "over_cap": false
  },
  {
   "code": "213420",
   "name": "덕산네오룩스",
   "weight": 0.01,
   "shares": 16.0,
   "amount": 466400.0,
   "over_cap": false
  },
  {
   "code": "388720",
   "name": "유일로보틱스",
   "weight": 0.01,
   "shares": 7.0,
   "amount": 450800.0,
   "over_cap": false
  },
  {
   "code": "082270",
   "name": "젬백스",
   "weight": 0.01,
   "shares": 42.0,
   "amount": 446460.0,
   "over_cap": false
  },
  {
   "code": "006120",
   "name": "SK디스커버리",
   "weight": 0.01,
   "shares": 9.0,
   "amount": 436050.0,
   "over_cap": false
  },
  {
   "code": "298050",
   "name": "HS효성첨단소재",
   "weight": 0.01,
   "shares": 3.0,
   "amount": 435000.0,
   "over_cap": false
  },
  {
   "code": "006040",
   "name": "동원산업",
   "weight": 0.01,
   "shares": 12.0,
   "amount": 414000.0,
   "over_cap": false
  },
  {
   "code": "005300",
   "name": "롯데칠성",
   "weight": 0.01,
   "shares": 4.0,
   "amount": 406400.0,
   "over_cap": false
  },
  {
   "code": "085620",
   "name": "미래에셋생명",
   "weight": 0.01,
   "shares": 24.0,
   "amount": 399600.0,
   "over_cap": false
  },
  {
   "code": "249420",
   "name": "일동제약",
   "weight": 0.01,
   "shares": 27.0,
   "amount": 391770.0,
   "over_cap": false
  },
  {
   "code": "293490",
   "name": "카카오게임즈",
   "weight": 0.01,
   "shares": 49.0,
   "amount": 387590.0,
   "over_cap": false
  },
  {
   "code": "038500",
   "name": "삼표시멘트",
   "weight": 0.01,
   "shares": 48.0,
   "amount": 377280.0,
   "over_cap": false
  },
  {
   "code": "253450",
   "name": "스튜디오드래곤",
   "weight": 0.01,
   "shares": 17.0,
   "amount": 355300.0,
   "over_cap": false
  },
  {
   "code": "100790",
   "name": "미래에셋벤처투자",
   "weight": 0.01,
   "shares": 23.0,
   "amount": 354200.0,
   "over_cap": false
  },
  {
   "code": "075580",
   "name": "세진중공업",
   "weight": 0.01,
   "shares": 27.0,
   "amount": 306450.0,
   "over_cap": false
  },
  {
   "code": "036830",
   "name": "솔브레인홀딩스",
   "weight": 0.0,
   "shares": 7.0,
   "amount": 229950.0,
   "over_cap": false
  },
  {
   "code": "000670",
   "name": "영풍",
   "weight": 0.0,
   "shares": 6.0,
   "amount": 213600.0,
   "over_cap": false
  },
  {
   "code": "016790",
   "name": "현대사료",
   "weight": 0.0,
   "shares": 65.0,
   "amount": 64610.0,
   "over_cap": false
  }
 ],
 "breach_summary": null,
 "cap": {
  "single_cap": null,
  "index_exception": true,
  "label": "기초지수 비중 복제 · 단일종목 상한 없음",
  "source": "자본시장법 시행령 §80(지수 비중까지 예외 허용)",
  "verified": true,
  "note": "기초지수 시가총액 비중을 그대로 복제. 강제 비중조절 대상 아님(지수 정기변경 시 조정)."
 }
}