{
 "ticker": "322400",
 "name": "HANARO e커머스",
 "manager": "HANARO",
 "source": "NH아문디 HANARO",
 "asof": "2026-07-20",
 "total_weight": 99.64,
 "count": 16,
 "holdings": [
  {
   "code": "035720",
   "name": "카카오",
   "weight": 20.75,
   "shares": 2958.0,
   "amount": 106192200.0,
   "over_cap": true
  },
  {
   "code": "035420",
   "name": "NAVER",
   "weight": 18.04,
   "shares": 486.0,
   "amount": 92340000.0,
   "over_cap": false
  },
  {
   "code": "069960",
   "name": "현대백화점",
   "weight": 11.35,
   "shares": 369.0,
   "amount": 58080600.0,
   "over_cap": false
  },
  {
   "code": "139480",
   "name": "이마트",
   "weight": 9.16,
   "shares": 588.0,
   "amount": 46863600.0,
   "over_cap": false
  },
  {
   "code": "377300",
   "name": "카카오페이",
   "weight": 8.77,
   "shares": 1097.0,
   "amount": 44867300.0,
   "over_cap": false
  },
  {
   "code": "257720",
   "name": "실리콘투",
   "weight": 7.63,
   "shares": 1083.0,
   "amount": 39042150.0,
   "over_cap": false
  },
  {
   "code": "030000",
   "name": "제일기획",
   "weight": 7.41,
   "shares": 2039.0,
   "amount": 37945790.0,
   "over_cap": false
  },
  {
   "code": "000120",
   "name": "CJ대한통운",
   "weight": 4.56,
   "shares": 322.0,
   "amount": 23345000.0,
   "over_cap": false
  },
  {
   "code": "093320",
   "name": "케이아이엔엑스",
   "weight": 2.29,
   "shares": 88.0,
   "amount": 11739200.0,
   "over_cap": false
  },
  {
   "code": "067160",
   "name": "SOOP",
   "weight": 2.24,
   "shares": 242.0,
   "amount": 11446600.0,
   "over_cap": false
  },
  {
   "code": "042000",
   "name": "카페24",
   "weight": 1.67,
   "shares": 530.0,
   "amount": 8548900.0,
   "over_cap": false
  },
  {
   "code": "060250",
   "name": "NHN KCP",
   "weight": 1.55,
   "shares": 639.0,
   "amount": 7936380.0,
   "over_cap": false
  },
  {
   "code": "064260",
   "name": "다날",
   "weight": 1.52,
   "shares": 1908.0,
   "amount": 7803720.0,
   "over_cap": false
  },
  {
   "code": "376300",
   "name": "디어유",
   "weight": 1.37,
   "shares": 349.0,
   "amount": 6997450.0,
   "over_cap": false
  },
  {
   "code": "035600",
   "name": "KG이니시스",
   "weight": 0.82,
   "shares": 447.0,
   "amount": 4206270.0,
   "over_cap": false
  },
  {
   "code": "094480",
   "name": "갤럭시아머니트리",
   "weight": 0.51,
   "shares": 530.0,
   "amount": 2591700.0,
   "over_cap": false
  }
 ],
 "breach_summary": {
  "cap_pct": 20.0,
  "verified": true,
  "count": 1,
  "total_sell": 262140000,
  "items": [
   {
    "code": "035720",
    "name": "카카오",
    "weight": 20.75,
    "cap_pct": 20.0,
    "excess_pp": 0.75,
    "sell_amount": 262140000
   }
  ]
 },
 "cap": {
  "single_cap": 0.2,
  "index_exception": false,
  "label": "단일종목 20% 상한",
  "source": "FnGuide_E_Commerce_Index_Methodology_Book_NH_v1.3.pdf | '특정종목의 지수내 비중이 20%를 넘을 경우 20%로 비중을 제한'; '6, 12월 선물옵션 만기일(D) 이후 4영업일(D+4)과 5영업일(D+5)에 정기변경'",
  "verified": true,
  "note": "5·11월말 종목선정 → 6·12월 선물옵션 만기일 D+4/D+5 정기변경(연2회). 유동시총 가중, 종목당 20% 상한"
 }
}